amazon/opentelemetry/distro/_aws_attribute_keys.py
amazon/opentelemetry/distro/_aws_metric_attribute_generator.py
amazon/opentelemetry/distro/_aws_resource_attribute_configurator.py
amazon/opentelemetry/distro/_aws_span_processing_util.py
amazon/opentelemetry/distro/_utils.py
amazon/opentelemetry/distro/always_record_sampler.py
amazon/opentelemetry/distro/attribute_propagating_span_processor.py
amazon/opentelemetry/distro/attribute_propagating_span_processor_builder.py
amazon/opentelemetry/distro/aws_batch_unsampled_span_processor.py
amazon/opentelemetry/distro/aws_lambda_span_processor.py
amazon/opentelemetry/distro/aws_metric_attributes_span_exporter.py
amazon/opentelemetry/distro/aws_metric_attributes_span_exporter_builder.py
amazon/opentelemetry/distro/aws_opentelemetry_configurator.py
amazon/opentelemetry/distro/aws_opentelemetry_distro.py
amazon/opentelemetry/distro/aws_span_metrics_processor.py
amazon/opentelemetry/distro/aws_span_metrics_processor_builder.py
amazon/opentelemetry/distro/llo_handler.py
amazon/opentelemetry/distro/metric_attribute_generator.py
amazon/opentelemetry/distro/otlp_udp_exporter.py
amazon/opentelemetry/distro/regional_resource_arn_parser.py
amazon/opentelemetry/distro/scope_based_exporter.py
amazon/opentelemetry/distro/scope_based_filtering_view.py
amazon/opentelemetry/distro/sqs_url_parser.py
amazon/opentelemetry/distro/version.py
amazon/opentelemetry/distro/code_correlation/__init__.py
amazon/opentelemetry/distro/code_correlation/code_attributes_span_processor.py
amazon/opentelemetry/distro/code_correlation/config.py
amazon/opentelemetry/distro/code_correlation/utils.py
amazon/opentelemetry/distro/code_correlation/internal/3rd.txt
amazon/opentelemetry/distro/code_correlation/internal/__init__.py
amazon/opentelemetry/distro/code_correlation/internal/packages_resolver.py
amazon/opentelemetry/distro/configuration/sql_dialect_keywords.json
amazon/opentelemetry/distro/exporter/aws/metrics/_cloudwatch_log_client.py
aws_opentelemetry_distro-0.14.2.dist-info/METADATA
aws_opentelemetry_distro-0.14.2.dist-info/WHEEL
aws_opentelemetry_distro-0.14.2.dist-info/entry_points.txt
aws_opentelemetry_distro-0.14.2.dist-info/RECORD
