Metadata-Version: 2.3
Name: aws-opentelemetry-distro
Version: 0.14.2
Summary: AWS OpenTelemetry Python Distro
Project-URL: Homepage, https://github.com/aws-observability/aws-otel-python-instrumentation/tree/main/aws-opentelemetry-distro
Author: Amazon Web Services
License: Apache-2.0
Classifier: Development Status :: 4 - Beta
Classifier: Intended Audience :: Developers
Classifier: License :: OSI Approved :: Apache Software License
Classifier: Programming Language :: Python
Classifier: Programming Language :: Python :: 3
Classifier: Programming Language :: Python :: 3.9
Classifier: Programming Language :: Python :: 3.10
Classifier: Programming Language :: Python :: 3.11
Classifier: Programming Language :: Python :: 3.12
Classifier: Programming Language :: Python :: 3.13
Requires-Python: >=3.9
Requires-Dist: opentelemetry-api==1.33.1
Requires-Dist: opentelemetry-distro==0.54b1
Requires-Dist: opentelemetry-exporter-otlp-proto-common==1.33.1
Requires-Dist: opentelemetry-exporter-otlp-proto-grpc==1.33.1
Requires-Dist: opentelemetry-exporter-otlp-proto-http==1.33.1
Requires-Dist: opentelemetry-instrumentation-aio-pika==0.54b1
Requires-Dist: opentelemetry-instrumentation-aiohttp-client==0.54b1
Requires-Dist: opentelemetry-instrumentation-aiokafka==0.54b1
Requires-Dist: opentelemetry-instrumentation-aiopg==0.54b1
Requires-Dist: opentelemetry-instrumentation-asgi==0.54b1
Requires-Dist: opentelemetry-instrumentation-asyncpg==0.54b1
Requires-Dist: opentelemetry-instrumentation-aws-lambda==0.54b1
Requires-Dist: opentelemetry-instrumentation-boto3sqs==0.54b1
Requires-Dist: opentelemetry-instrumentation-boto==0.54b1
Requires-Dist: opentelemetry-instrumentation-botocore==0.54b1
Requires-Dist: opentelemetry-instrumentation-cassandra==0.54b1
Requires-Dist: opentelemetry-instrumentation-celery==0.54b1
Requires-Dist: opentelemetry-instrumentation-confluent-kafka==0.54b1
Requires-Dist: opentelemetry-instrumentation-dbapi==0.54b1
Requires-Dist: opentelemetry-instrumentation-django==0.54b1
Requires-Dist: opentelemetry-instrumentation-elasticsearch==0.54b1
Requires-Dist: opentelemetry-instrumentation-falcon==0.54b1
Requires-Dist: opentelemetry-instrumentation-fastapi==0.54b1
Requires-Dist: opentelemetry-instrumentation-flask==0.54b1
Requires-Dist: opentelemetry-instrumentation-grpc==0.54b1
Requires-Dist: opentelemetry-instrumentation-httpx==0.54b1
Requires-Dist: opentelemetry-instrumentation-jinja2==0.54b1
Requires-Dist: opentelemetry-instrumentation-kafka-python==0.54b1
Requires-Dist: opentelemetry-instrumentation-logging==0.54b1
Requires-Dist: opentelemetry-instrumentation-mysql==0.54b1
Requires-Dist: opentelemetry-instrumentation-mysqlclient==0.54b1
Requires-Dist: opentelemetry-instrumentation-pika==0.54b1
Requires-Dist: opentelemetry-instrumentation-psycopg2==0.54b1
Requires-Dist: opentelemetry-instrumentation-pymemcache==0.54b1
Requires-Dist: opentelemetry-instrumentation-pymongo==0.54b1
Requires-Dist: opentelemetry-instrumentation-pymysql==0.54b1
Requires-Dist: opentelemetry-instrumentation-pyramid==0.54b1
Requires-Dist: opentelemetry-instrumentation-redis==0.54b1
Requires-Dist: opentelemetry-instrumentation-remoulade==0.54b1
Requires-Dist: opentelemetry-instrumentation-requests==0.54b1
Requires-Dist: opentelemetry-instrumentation-sqlalchemy==0.54b1
Requires-Dist: opentelemetry-instrumentation-sqlite3==0.54b1
Requires-Dist: opentelemetry-instrumentation-starlette==0.54b1
Requires-Dist: opentelemetry-instrumentation-system-metrics==0.54b1
Requires-Dist: opentelemetry-instrumentation-tornado==0.54b1
Requires-Dist: opentelemetry-instrumentation-tortoiseorm==0.54b1
Requires-Dist: opentelemetry-instrumentation-urllib3==0.54b1
Requires-Dist: opentelemetry-instrumentation-urllib==0.54b1
Requires-Dist: opentelemetry-instrumentation-wsgi==0.54b1
Requires-Dist: opentelemetry-instrumentation==0.54b1
Requires-Dist: opentelemetry-processor-baggage==0.54b1
Requires-Dist: opentelemetry-propagator-aws-xray==1.0.1
Requires-Dist: opentelemetry-propagator-b3==1.33.1
Requires-Dist: opentelemetry-propagator-jaeger==1.33.1
Requires-Dist: opentelemetry-propagator-ot-trace==0.54b1
Requires-Dist: opentelemetry-sdk-extension-aws==2.1.0
Requires-Dist: opentelemetry-sdk==1.33.1
Provides-Extra: patch
Requires-Dist: botocore~=1.0; extra == 'patch'
Provides-Extra: test
